{
  "swagger": "2.0",
  "info": {
    "title": "SGO - Sistema Gerenciador de Obras",
    "description": "API de desenvolvimento do Sistema Gerenciador de Obras",
    "version": "1.0.0"
  },
  "host": "localhost:4000",
  "basePath": "/",
  "schemes": [
    "http"
  ],
  "securityDefinitions": {
    "apiKeyAuth": {
      "type": "apiKey",
      "in": "header",
      "name": "chaveapi",
      "description": "Chave para autorização da API"
    }
  },
  "paths": {
    "/clientes/listar": {
      "get": {
        "description": "",
        "responses": {
          "default": {
            "description": ""
          }
        }
      }
    },
    "/clientes/obter/{idCli}": {
      "get": {
        "description": "",
        "parameters": [
          {
            "name": "idCli",
            "in": "path",
            "required": true,
            "type": "string"
          }
        ],
        "responses": {
          "default": {
            "description": ""
          }
        }
      }
    },
    "/clientes/alterar/": {
      "put": {
        "description": "",
        "responses": {
          "default": {
            "description": ""
          }
        }
      }
    },
    "/clientes/gravar": {
      "post": {
        "description": "",
        "responses": {
          "default": {
            "description": ""
          }
        }
      }
    },
    "/clientes/excluir/{idCli}": {
      "delete": {
        "description": "",
        "parameters": [
          {
            "name": "idCli",
            "in": "path",
            "required": true,
            "type": "string"
          }
        ],
        "responses": {
          "default": {
            "description": ""
          }
        }
      }
    }
  },
  "components": {
    "schemas": {
      "funcionario": {}
    }
  }
}